sqltap/__init__.py
sqltap/profiling.py
sqltap/sqltap.py
sqltap/wsgi.py
sqltap/templates/html.mako
sqltap/templates/text.mako
sqltap/templates/wsgi.mako
sqltap_profiler-1.2.0.dist-info/licenses/LICENSE
sqltap_profiler-1.2.0.dist-info/METADATA
sqltap_profiler-1.2.0.dist-info/WHEEL
sqltap_profiler-1.2.0.dist-info/top_level.txt
sqltap_profiler-1.2.0.dist-info/RECORD
