Metadata-Version: 2.4
Name: sqltap-profiler
Version: 1.2.0
Summary: Enhanced SQL profiling and introspection for applications using sqlalchemy
Author-email: Bruno Cardoso <bruno@skywatch.com>
Maintainer-email: Bruno Cardoso <bruno@skywatch.com>
License: Apache-2.0
Project-URL: Homepage, https://github.com/brunobcardoso/sqltap-profiler
Project-URL: Repository, https://github.com/brunobcardoso/sqltap-profiler
Project-URL: Issues, https://github.com/brunobcardoso/sqltap-profiler/issues
Project-URL: Documentation, https://github.com/brunobcardoso/sqltap-profiler#readme
Keywords: sqlalchemy,sql,profiling,debugging,performance
Classifier: Development Status :: 5 - Production/Stable
Classifier: Intended Audience :: Developers
Classifier: License :: OSI Approved :: Apache Software License
Classifier: Operating System :: OS Independent
Classifier: Programming Language :: Python :: 3
Classifier: Programming Language :: Python :: 3.7
Classifier: Programming Language :: Python :: 3.8
Classifier: Programming Language :: Python :: 3.9
Classifier: Programming Language :: Python :: 3.10
Classifier: Programming Language :: Python :: 3.11
Classifier: Programming Language :: Python :: 3.12
Classifier: Topic :: Database
Classifier: Topic :: Software Development :: Debuggers
Classifier: Topic :: Software Development :: Testing
Requires-Python: >=3.7
License-File: LICENSE
Requires-Dist: SQLAlchemy>=1.4
Requires-Dist: Mako>=0.4.1
Requires-Dist: Werkzeug>=0.9.6
Requires-Dist: sqlparse>=0.1.15
Dynamic: license-file
